aigbook/__init__.py
aigbook/aigbook-gui.py
aigbook/book.py
aigbook/gebiqu.py
aigbook/zw81.py
aigbook-1.0.0.6.dist-info/LICENSE
aigbook-1.0.0.6.dist-info/METADATA
aigbook-1.0.0.6.dist-info/WHEEL
aigbook-1.0.0.6.dist-info/entry_points.txt
aigbook-1.0.0.6.dist-info/top_level.txt
aigbook-1.0.0.6.dist-info/RECORD
