Metadata-Version: 2.1
Name: aigbook
Version: 1.0.0.6
Summary: UNKNOWN
Home-page: UNKNOWN
Author: Yaronzz
Author-email: yaronhuang@foxmail.com
License: MIT Licence
Platform: any
Requires-Dist: requests
Requires-Dist: aigpy
Requires-Dist: lxml
Requires-Dist: prettytable
